[{"text": ["Charts in django Web Applications"], "childNum": 0, "tag": "h2", "senID": 0, "childList": []}, {"text": ["I want to Embed a chart in a Web Application developed using django."], "childNum": 0, "tag": "p", "senID": 1, "childList": []}, {"text": ["I have come across Google charts API, ReportLab, PyChart, MatPlotLib and ChartDirector"], "childNum": 5, "tag": "p", "senID": 2, "childList": [{"text": "Google charts API", "tag": "a", "pos": 0, "childList": [], "childNum": 0, "href": "http://code.google.com/p/google-chartwrapper/"}, {"href": "http://code.djangoproject.com/wiki/Charts", "text": "ReportLab", "childNum": 0, "tag": "a", "childList": []}, {"href": "http://home.gna.org/pychart/", "text": "PyChart", "childNum": 0, "tag": "a", "childList": []}, {"href": "http://matplotlib.sourceforge.net/", "text": "MatPlotLib", "childNum": 0, "tag": "a", "childList": []}, {"href": "http://www.advsofteng.com/?gid=misc&gclid=CJLaibjeiJkCFQMwpAodXkETng", "text": "ChartDirector", "childNum": 0, "tag": "a", "childList": []}]}, {"text": ["I want to do it in the server side rather than send the AJAX request to Google chart APIs, as I also want to embed the chart into the PDF."], "childNum": 0, "tag": "p", "senID": 3, "childList": []}, {"text": ["Which is the best option to use, and what are the relative merits and demerits of one over the other."], "childNum": 0, "tag": "p", "senID": 4, "childList": []}]