[{"text": ["What are the pros and cons of the various Python implementations?"], "childNum": 0, "tag": "h2", "senID": 0, "childList": []}, {"text": ["I am relatively new to Python, and I have always used the standard cpython (v2.5) implementation.  "], "childNum": 0, "tag": "p", "senID": 1, "childList": []}, {"text": ["I've been wondering about the other implementations though, particularly Jython and IronPython.", "What makes them better?", "What makes them worse?", "What other implementations are there?"], "childNum": 0, "tag": "p", "senID": 2, "childList": []}, {"text": ["I guess what I'm looking for is a summary and list of pros and cons for each implementation."], "childNum": 0, "tag": "p", "senID": 3, "childList": []}]