[{"text": ["c style loop for in python"], "childNum": 0, "tag": "h2", "senID": 0, "childList": []}, {"text": ["I need c style loop for:"], "childNum": 0, "tag": "p", "senID": 1, "childList": []}, {"code": "<pre>\n<code>\n for( int i = 0; i &lt; n; i++ )\n</code>\n</pre>\n", "senID": 2}, {"text": ["There's equivalent i've found, but when iterating with big number of iterations, it consumes a lot of memory."], "childNum": 0, "tag": "p", "senID": 3, "childList": []}, {"code": "<pre>\n<code>\n for i in range( 0, n ):\n</code>\n</pre>\n", "senID": 4}, {"text": ["Is there any other equivalent?"], "childNum": 0, "tag": "p", "senID": 5, "childList": []}]