[{"text": ["Define css class in django Forms"], "childNum": 0, "tag": "h2", "senID": 0, "childList": []}, {"text": ["Assume I have a form"], "childNum": 0, "tag": "p", "senID": 1, "childList": []}, {"code": "<pre>\n<code>\n class SampleClass(forms.Form):\n    name = forms.CharField(max_length=30)\n    age = forms.IntegerField()\n    django_hacker = forms.BooleanField(required=False)\n</code>\n</pre>\n", "senID": 2}, {"text": ["Is there a way for me to define css classes on each field such that I can then use jQuery based on class in my rendered page?"], "childNum": 0, "tag": "p", "senID": 3, "childList": []}, {"text": ["I was hoping not to have to manually build the form."], "childNum": 0, "tag": "p", "senID": 4, "childList": []}]