[{"text": ["right way to run some code with timeout in Python"], "childNum": 0, "tag": "h2", "senID": 0, "childList": []}, {"text": ["I looked online and found some SO discussing and ActiveState recipes for running some code with a timeout.", "It looks there are some common approaches:"], "childNum": 0, "tag": "p", "senID": 1, "childList": []}, {"tag": "ul", "num": 3, "lis": [{"text": "Use thread that run the code, and ", "tag": "none", "senID": 2}, {"text": "Use ", "tag": "none", "senID": 3}, {"text": "Use subprocess with timeout - but this is ", "tag": "none", "senID": 4}]}, {"text": ["So, what is the right way?", "I'm not asking about workarounds (eg use Twisted and async IO), but actual way to solve actual problem - I have some function and I want to run it only with some timeout.", "If timeout elapsed, I want control back.", "And I want it to work on Linux and Windows."], "childNum": 1, "tag": "p", "senID": 5, "childList": [{"text": "the right way", "childNum": 0, "tag": "strong", "pos": 0, "childList": []}]}]