[{"text": ["How to have data structure with both tuple and dictionary characteristic"], "childNum": 0, "tag": "h2", "senID": 0, "childList": []}, {"text": ["By refering code at"], "childNum": 0, "tag": "p", "senID": 1, "childList": []}, {"text": ["http://initd.org/psycopg/docs/extras.html#dictionary-like-cursor"], "childNum": 1, "tag": "p", "senID": 2, "childList": [{"text": "http://initd.org/psycopg/docs/extras.html#dictionary-like-cursor", "tag": "a", "pos": 0, "childList": [], "childNum": 0, "href": "http://initd.org/psycopg/docs/extras.html#dictionary-like-cursor"}]}, {"code": "<pre>\n<code>\n &gt;&gt;&gt; rec['data']\n\"abc'def\"\n&gt;&gt;&gt; rec[2]\n\"abc'def\"\n</code>\n</pre>\n", "senID": 3}, {"text": ["I was wondering how they manage to make a data structure having both tuple and dictionary characteristic?"], "childNum": 0, "tag": "p", "senID": 4, "childList": []}]