[{"text": ["How to split python script in parts and to import the parts in a loop?"], "childNum": 0, "tag": "h2", "senID": 0, "childList": []}, {"text": ["First, sorry for my stupid title :) And here is my problem.. Actually it's not a problem.", "Everything works, but I want to have better structure..."], "childNum": 0, "tag": "p", "senID": 1, "childList": []}, {"text": ["I have a python script with a loop \"looped\" each second.", "In the loop there are many many IFs.", "Is it possible to put each IF in a separate file and then to include it in the loop?", "So this way every time the loop is \"looped\", all the IFs will be passed, too.."], "childNum": 0, "tag": "p", "senID": 2, "childList": []}, {"text": ["There are too many conditions in my script and all of them are different generally from the otheres so I want to have some kind of folder with modules - mod_wheather.py, mod_sport.py, mod_horoscope.py, etc.. "], "childNum": 0, "tag": "p", "senID": 3, "childList": []}, {"text": ["Thanks in advance.", "I hope I wrote everything understandable.."], "childNum": 0, "tag": "p", "senID": 4, "childList": []}, {"text": ["EDIT:\nHere is a structural example of what I have now:"], "childNum": 1, "tag": "p", "senID": 5, "childList": [{"text": "EDIT:", "childNum": 0, "tag": "strong", "pos": 0, "childList": []}]}, {"code": "<pre>\n<code>\n while True:\n   if condition=='news':\n      #do something\n\n   if condition=='sport':\n      #so something else\n\n   time.sleep(1)\n</code>\n</pre>\n", "senID": 6}, {"text": ["It will be good if I can have something like this:"], "childNum": 0, "tag": "p", "senID": 7, "childList": []}, {"code": "<pre>\n<code>\n while True:\n   import mod_news\n   import mod_sport\n\n   time.sleep(1)\n</code>\n</pre>\n", "senID": 8}, {"text": ["And these IFs from the first example to be separated in files mod_news.py, mod_sport.py..."], "childNum": 0, "tag": "p", "senID": 9, "childList": []}]