[{"text": ["PyQt4 signals and slots"], "childNum": 0, "tag": "h2", "senID": 0, "childList": []}, {"text": ["I am writing my first Python app with PyQt4.", "I have a MainWindow and a Dialog class, which is a part of MainWindow class:"], "childNum": 0, "tag": "p", "senID": 1, "childList": []}, {"code": "<pre>\n<code>\n self.loginDialog = LoginDialog();\n</code>\n</pre>\n", "senID": 2}, {"text": ["I use slots and signals.", "Here's a connection made in MainWindow:"], "childNum": 0, "tag": "p", "senID": 3, "childList": []}, {"code": "<pre>\n<code>\n QtCore.QObject.connect(self.loginDialog, QtCore.SIGNAL(\"aa(str)\"), self.login)\n</code>\n</pre>\n", "senID": 4}, {"text": ["And I try to emit signal inside the Dialog class (I'm sure it is emitted):"], "childNum": 0, "tag": "p", "senID": 5, "childList": []}, {"code": "<pre>\n<code>\n self.emit(QtCore.SIGNAL(\"aa\"), \"jacek\")\n</code>\n</pre>\n", "senID": 6}, {"text": ["Unfortunately, slot is not invoked.", "I tried with no arguments as well, different styles of emitting signal.", "No errors, no warnings in the code.", "What might be the problem?"], "childNum": 0, "tag": "p", "senID": 7, "childList": []}]