[{"text": ["Is there a way to convert indentation in Python code to braces?"], "childNum": 0, "tag": "h2", "senID": 0, "childList": []}, {"text": ["I am a totally blind programmer who would like to learn Python.", "Unfortunately the fact that code blocks are represented with different levels of indentation is a major stumbling block.", "I was wondering if there were any tools available that would allow me to write code using braces or some other code block delimiter and then convert that format into a properly indented representation that the Python interpreter could use?"], "childNum": 0, "tag": "p", "senID": 1, "childList": []}]