[{"text": ["Python: Test if an argument is an integer"], "childNum": 0, "tag": "h2", "senID": 0, "childList": []}, {"text": ["I want to write a python script that takes 3 parameters.", "The first parameter is a string, the second is an integer, and the third is also an integer."], "childNum": 0, "tag": "p", "senID": 1, "childList": []}, {"text": ["I want to put conditional checks at the start to ensure that the proper number of arguments are provided, and they are the right type before proceeding."], "childNum": 0, "tag": "p", "senID": 2, "childList": []}, {"text": ["I know we can use sys.argv to get the argument list, but I don't know how to test that a parameter is an integer before assigning it to my local variable for use."], "childNum": 0, "tag": "p", "senID": 3, "childList": []}, {"text": ["Any help would be greatly appreciated."], "childNum": 0, "tag": "p", "senID": 4, "childList": []}]