[{"text": ["Options for read-only binary flat-file storage using Python"], "childNum": 0, "tag": "h2", "senID": 0, "childList": []}, {"text": ["I have been tasked with setting up a flat-file SKU database for use on embedded devices with limited storage and processor speed."], "childNum": 0, "tag": "p", "senID": 1, "childList": []}, {"text": ["Basically the data I need to store consists of the following:"], "childNum": 0, "tag": "p", "senID": 2, "childList": []}, {"text": ["SKU\nDescription\nLocation\nPrice\nQty"], "childNum": 0, "tag": "p", "senID": 3, "childList": []}, {"text": ["The file will consist of several million records."], "childNum": 0, "tag": "p", "senID": 4, "childList": []}, {"text": ["The most important considerations are storage space and retrieval time.", "Records will only need to be retrieved by SKU and it will be read-only, so the file can be sorted by SKU."], "childNum": 0, "tag": "p", "senID": 5, "childList": []}, {"text": ["I would like to access this data with Python.", "So my questions comes down to this."], "childNum": 0, "tag": "p", "senID": 6, "childList": []}, {"text": ["Are there existing Python libraries that can provide this functionality for me, or do I need to roll my own?"], "childNum": 0, "tag": "p", "senID": 7, "childList": []}, {"text": ["If the answer comes down to roll my own, does anyone have a suggestions, or good references for doing so?"], "childNum": 0, "tag": "p", "senID": 8, "childList": []}]