[{"text": ["What are some good web resources for learning Object-Oriented Programming?"], "childNum": 0, "tag": "h2", "senID": 0, "childList": []}, {"text": ["I've started programming more in OO style than ever (Python).", "Any good web resources I could read?", "I need help constructing and modelling objects, relations, interfaces etc.", "Not only dry theory (I've read that), but something easy to grasp (examples would be nice), do you know any site or a good book?"], "childNum": 2, "tag": "p", "senID": 1, "childList": [{"text": "I need help constructing and modelling objects, relations, interfaces etc.", "childNum": 0, "tag": "strong", "pos": 2, "childList": []}, {"text": "dry theory", "childNum": 0, "tag": "em", "pos": 3, "childList": []}]}]