[{"text": ["iterating through dictionary with list as values in python"], "childNum": 0, "tag": "h2", "senID": 0, "childList": []}, {"text": ["Say you have a dictionary as shown:"], "childNum": 0, "tag": "p", "senID": 1, "childList": []}, {"text": ["d = { 'a': ['s','b'], 'b': ['x1','y1','z1'] }"], "childNum": 1, "tag": "p", "senID": 2, "childList": [{"text": "d = { 'a': ['s','b'], 'b': ['x1','y1','z1'] }", "childNum": 0, "tag": "code", "pos": 0, "childList": []}]}, {"text": ["How could i produce the following output:"], "childNum": 0, "tag": "p", "senID": 3, "childList": []}, {"text": ["s, x1, b, y1, z1"], "childNum": 1, "tag": "p", "senID": 4, "childList": [{"text": "s, x1, b, y1, z1", "childNum": 0, "tag": "code", "pos": 0, "childList": []}]}, {"text": ["Thanks"], "childNum": 0, "tag": "p", "senID": 5, "childList": []}]