[{"text": ["High quality, simple random password generator"], "childNum": 0, "tag": "h2", "senID": 0, "childList": []}, {"text": ["I'm interested in creating a very simple, high (cryptographic) quality random password generator.", "Is there a better way to do this?"], "childNum": 0, "tag": "p", "senID": 1, "childList": []}, {"code": "<pre>\n<code>\n import os, random, string\n\nlength = 13\nchars = string.ascii_letters + string.digits + '!@#$%^&amp;*()'\nrandom.seed = (os.urandom(1024))\n\nprint ''.join(random.choice(chars) for i in range(length))\n</code>\n</pre>\n", "senID": 2}]