[{"text": ["From List of Dictionary To Dictionary"], "childNum": 0, "tag": "h2", "senID": 0, "childList": []}, {"text": ["I have some problem with my function."], "childNum": 0, "tag": "p", "senID": 1, "childList": []}, {"text": ["I do an SQL Query to obtain a list that have some dictionary with only a key/value element.", "This is a sample of my output:"], "childNum": 0, "tag": "p", "senID": 2, "childList": []}, {"code": "<pre>\n<code>\n myDictList = [{'id': 55, 'sigla': 'SNG'}, {'id': 62, 'sigla': 'TRP'}, \n {'id': 71, 'sigla': 'PCNIM'},  {'id': 72, 'sigla': 'pc2ni'}, \n {'id': 73, 'sigla': 'ccas'}, {'id': 74, 'sigla': 'ased1'}, \n {'id': 75, 'sigla': '131s'}, {'id': 76, 'sigla': 'r888'}, \n {'id': 56, 'sigla': 'DBL'}]\n</code>\n</pre>\n", "senID": 3}, {"text": ["The id are unique (for SQL constraint)."], "childNum": 1, "tag": "p", "senID": 4, "childList": [{"text": "id", "childNum": 0, "tag": "code", "pos": 0, "childList": []}]}, {"text": ["I've build a list of id in that way"], "childNum": 1, "tag": "p", "senID": 5, "childList": [{"text": "id", "childNum": 0, "tag": "code", "pos": 0, "childList": []}]}, {"code": "<pre>\n<code>\n r_id_list = list(rid['id'] for rid in roomList)\n</code>\n</pre>\n", "senID": 6}, {"text": ["Now, i would build a dict.", "like that from myDictList:"], "childNum": 1, "tag": "p", "senID": 7, "childList": [{"text": "myDictList", "childNum": 0, "tag": "code", "pos": 1, "childList": []}]}, {"code": "<pre>\n<code>\n {55:'SNG',62:'TRP',71:'PCNIM'.... and so on}\n</code>\n</pre>\n", "senID": 8}, {"text": ["More over, i want to avoid part of code like that:"], "childNum": 0, "tag": "p", "senID": 9, "childList": []}, {"code": "<pre>\n<code>\n finalDict = {}\nfor element in myDictList:\n    finalDict.update({element['id']:element['sigla']})\n</code>\n</pre>\n", "senID": 10}, {"text": ["I want to do that for some reasons:"], "childNum": 0, "tag": "p", "senID": 11, "childList": []}, {"tag": "ul", "num": 2, "lis": [{"text": "I don't want to do two separate query to obtain some data that i can retrive with one", "tag": "none", "senID": 12}, {"text": "I don't want to iterate to every list element for retrive ", "tag": "none", "senID": 13}]}, {"text": ["Some suggestion for a compact code that will not include a for cycle inside a for cycle, and increase the complexity?"], "childNum": 2, "tag": "p", "senID": 14, "childList": [{"text": "for", "childNum": 0, "tag": "code", "pos": 0, "childList": []}, {"text": "for", "childNum": 0, "tag": "code", "childList": []}]}]