[{"text": ["split command question"], "childNum": 0, "tag": "h2", "senID": 0, "childList": []}, {"text": ["I got problem with using split command.", "The input string is as follows:"], "childNum": 0, "tag": "p", "senID": 1, "childList": []}, {"code": "<pre>\n<code>\n 080821_HWI-EAS301_0002_30ALBAAXX:1:8:1649:2027  83  chr10   42038185    255 36M =   42037995    -225    GCCAGGTTTAATAAATTATTTATAGAATACTGCATC    @?DDEAEFDAD@FBG@CDA?DBCDEECD@D?CBA&gt;A    NM:i:0  MD:Z:36\n</code>\n</pre>\n", "senID": 2}, {"text": ["I want to grab '2027' from this string\nmy command is: line.split(':',4)[1].split()[0]\nHowever, it doesn't work.", "The output is '1'"], "childNum": 1, "tag": "p", "senID": 3, "childList": [{"text": "line.split(':',4)[1].split()[0]", "childNum": 0, "tag": "code", "pos": 0, "childList": []}]}, {"text": ["Then I switch to line.split(':',4) \nAnd output is still '1', and I see the first-step split is already problematic."], "childNum": 1, "tag": "p", "senID": 4, "childList": [{"text": "line.split(':',4)", "childNum": 0, "tag": "code", "pos": 0, "childList": []}]}, {"text": ["However, when I try line.split(':',1), I got expected result as:"], "childNum": 1, "tag": "p", "senID": 5, "childList": [{"text": "line.split(':',1)", "childNum": 0, "tag": "code", "pos": 0, "childList": []}]}, {"code": "<pre>\n<code>\n 1:8:1649:2027   83  chr10   42038185    255 36M =   42037995-225    GCCAGGTTTAATAAATTATTTATAGAATACTGCATC    @?DDEAEFDAD@FBG@CDA?DBCDEECD@D?CBA&gt;A    NM:i:0  MD:Z:36\n</code>\n</pre>\n", "senID": 6}, {"text": ["I'm confused by this split command!", "(I asked the similar question before, and split command worked at that time)\nthanks"], "childNum": 0, "tag": "p", "senID": 7, "childList": []}]