[{"text": ["How to shorten this expression using regex"], "childNum": 0, "tag": "h2", "senID": 0, "childList": []}, {"text": ["I have the following if statement:"], "childNum": 0, "tag": "p", "senID": 1, "childList": []}, {"code": "<pre>\n<code>\n if not fileName.startswith(\".\") and re.search(\"(.exe|.EXE)$\", fileName) is not None and not fileName.endswith(\"-xyz.exe\"):\n    pass\n</code>\n</pre>\n", "senID": 2}, {"text": ["Essentially, I would like to check that the filename does not start with a period and ends with either .exe or .EXE extension, but not with the -xyz.exe extension.", "How can I get rid of the startswith and endswith and combine those two checks into the regex itself.  "], "childNum": 0, "tag": "p", "senID": 3, "childList": []}, {"text": ["UPDATE: I ask because I want to learn more about regex.", "Depending on the readability, I will determine if that would be worth making it more concise or not."], "childNum": 0, "tag": "p", "senID": 4, "childList": []}, {"text": ["UPDATE 2: I ran into this situation.", "I always look for opportunities to learn more about regex.", "This seems like a good opportunity, so I TRIED to do it MYSELF FIRST until I got stuck.", "Please do not give non-regex solution or echo Mark Pilgrim's statement about \"now you have 2 problems\", because anyone could have done that.", "Instead, prove it to me that now I have 2 problems, just like Mark Pilgrim continued with his lesson.", "Or show me that it's slick. "], "childNum": 0, "tag": "p", "senID": 5, "childList": []}]