[{"text": ["How Big can a Python Array Get?"], "childNum": 0, "tag": "h2", "senID": 0, "childList": []}, {"text": ["In Python,"], "childNum": 0, "tag": "p", "senID": 1, "childList": []}, {"text": ["how big can an array/list get?", "I need an array about 12000 elements large... is that okay?", "- will I still be able to run array/list methods such as sorting, etc?"], "childNum": 0, "tag": "p", "senID": 2, "childList": []}, {"text": ["Thanks so much,\nEd"], "childNum": 0, "tag": "p", "senID": 3, "childList": []}]