[{"text": ["What's an easy way to implement a --quiet option in a python script"], "childNum": 0, "tag": "h2", "senID": 0, "childList": []}, {"text": ["Am working on a command line python script - throughout the script, I have a lot of information I am print-ing to the terminal window so that I may follow along with what is happening."], "childNum": 1, "tag": "p", "senID": 1, "childList": [{"text": "print", "childNum": 0, "tag": "code", "pos": 0, "childList": []}]}, {"text": ["Using OptionParser I want to add a --quiet option so I can silence all the output.", "I am looking for a pythonic way to go about implementing this throughout the script so that I don't end up doing something like:"], "childNum": 3, "tag": "p", "senID": 2, "childList": [{"text": "OptionParser", "childNum": 0, "tag": "code", "pos": 0, "childList": []}, {"text": "--quiet", "childNum": 0, "tag": "code", "pos": -1, "childList": []}, {"text": "don't", "childNum": 0, "tag": "em", "pos": 1, "childList": []}]}, {"code": "<pre>\n<code>\n if not QUIET: # global variable set by OptionParser\n    print \" my output \"\n</code>\n</pre>\n", "senID": 3}, {"text": ["Am new to python and sure there is a better way.", "Ideas?  "], "childNum": 0, "tag": "p", "senID": 4, "childList": []}]