[{"text": ["Speeding up regular expressions in Python"], "childNum": 0, "tag": "h2", "senID": 0, "childList": []}, {"text": ["I need to quickly extract text from HTML files.", "I am using the following regular expressions instead of a full-fledged parser since I need to be fast rather than accurate (I have more than a terabyte of text).", "The profiler shows that most of the time in my script is spent in the re.sub procedure.", "What are good ways of speeding up my process?", "I can implement some portions in C, but I wonder whether that will help given that the time is spent inside re.sub, which I think would be efficiently implemented."], "childNum": 1, "tag": "p", "senID": 1, "childList": [{"text": "inside", "childNum": 0, "tag": "em", "pos": 4, "childList": []}]}, {"code": "<pre>\n<code>\n # Remove scripts, styles, tags, entities, and extraneous spaces:\nscriptRx    = re.compile(\"&lt;script.*?/script&gt;\", re.I)\nstyleRx     = re.compile(\"&lt;style.*?/style&gt;\", re.I)\ntagsRx      = re.compile(\"&lt;[!/]?[a-zA-Z-]+[^&lt;&gt;]*&gt;\")\nentitiesRx  = re.compile(\"&amp;[0-9a-zA-Z]+;\")\nspacesRx    = re.compile(\"\\s{2,}\")\n....\ntext = scriptRx.sub(\" \", text)\ntext = styleRx.sub(\" \", text)\n....\n</code>\n</pre>\n", "senID": 2}, {"text": ["Thanks!"], "childNum": 0, "tag": "p", "senID": 3, "childList": []}]