[{"text": ["How to implement a ilike Facebook system without user authentication and still prevent users from cheating?"], "tag": "h2", "senID": 0}, {"text": ["I am trying to implement something done in almost any website out there : a 'ilike' button (like Facebook) that does not require user authetication to be used for any article of my website written in Grails."], "tag": "p", "senID": 1}, {"text": ["I don't want to use any external solution, so I need to implement it myself (or use a grails plugin)."], "tag": "p", "senID": 2}, {"text": ["So my question is : What does it take to implement this 'ilike' button and prevent users from cheating at the maximum?", "For instance, do I need to store local cookies (I suppose yes)?", "Do I need to check the session ID and IP of the HTTP request?"], "tag": "p", "senID": 3}, {"text": ["What are the well-known implementations for online polls for instance?"], "tag": "p", "senID": 4}, {"text": ["Thank you very much for your help."], "tag": "p", "senID": 5}]