[[{"text": ["No, as there is no way to decide whether"], "childNum": 0, "tag": "p", "senID": 0, "childList": []}, {"code": "<pre>\n<code>\n my_func(a, b)\n</code>\n</pre>\n", "senID": 1}, {"text": ["means"], "childNum": 0, "tag": "p", "senID": 2, "childList": []}, {"code": "<pre>\n<code>\n args = [], args2 = [a,b] # or ..\nargs = [a], args2 = [b]  # or ..\nargs = [a,b], args2 = []\n</code>\n</pre>\n", "senID": 3}, {"text": ["Instead, simply let the function take two lists as arguments."], "childNum": 0, "tag": "p", "senID": 4, "childList": []}], [{"text": ["You should use lists.", "That way, it's obvious which item goes in which argument:"], "childNum": 0, "tag": "p", "senID": 0, "childList": []}, {"code": "<pre>\n<code>\n def my_func(args1, args2):\n    for a in args1:\n        print a\n    for b in args2:\n        print b\n\nmy_func([1, 2, 3], [4, 5, 6])\n</code>\n</pre>\n", "senID": 1}], [{"text": ["You could use an array (or whatever Python's name for an array is) for each argument.", "Otherwise, there's no way for Python to know where to split each set of variable length arguments."], "childNum": 0, "tag": "p", "senID": 0, "childList": []}], [{"text": ["How would you like to call the function?", "why not use two arrys or dicts?"], "childNum": 0, "tag": "p", "senID": 0, "childList": []}], [{"text": ["No that doesn't even make sense.", "What would determine what goes in the first list and what goes in the second?", "You can pass keyword arguments as well, though (in case you didn't know already):"], "childNum": 0, "tag": "p", "senID": 0, "childList": []}, {"code": "<pre>\n<code>\n def func(*args **kwargs):\n    pass\n</code>\n</pre>\n", "senID": 1}, {"text": ["What exactly is it that you are trying to accomplish?"], "childNum": 0, "tag": "p", "senID": 2, "childList": []}], [{"text": ["Just split the list after it is received by the function.", "For example, to split the list (roughly) in halves:"], "childNum": 0, "tag": "p", "senID": 0, "childList": []}, {"code": "<pre>\n<code>\n def my_func(*args):\n    l=len(args)//2\n    args1,args2 = args[:l],args[l:]\n</code>\n</pre>\n", "senID": 1}]]