[[{"text": ["You're calling the function as a method.", "Add \"self\" as the first argument and it'll work."], "childNum": 0, "tag": "p", "senID": 0, "childList": []}], [{"text": ["You have not posted all of your code.", "The code you didn't post looks like this:"], "childNum": 0, "tag": "p", "senID": 0, "childList": []}, {"code": "<pre>\n<code>\n class SomeClass:\n\n    def gcd(a,b):\n        if a == 0:\n                return b\n        while b != 0:\n                if a &gt; b:\n                        a = a - b\n                else:\n                        b = b - a\n        return a \n\nG = SomeClass()\nG.gcd(1,2)\n</code>\n</pre>\n", "senID": 1}, {"text": ["In python, when you define a class member function, the class instance is automatically passed to the function.", "Change your code to look like this:"], "childNum": 0, "tag": "p", "senID": 2, "childList": []}, {"code": "<pre>\n<code>\n class SomeClass:\n\n    def gcd(a,b):\n        if a == 0:\n                return b\n        while b != 0:\n                if a &gt; b:\n                        a = a - b\n                else:\n                        b = b - a\n        return a \n\nG = SomeClass()\nG.gcd(1,2)\n</code>\n</pre>\n", "senID": 3}, {"text": ["or better yet"], "childNum": 0, "tag": "p", "senID": 4, "childList": []}, {"code": "<pre>\n<code>\n def gcd( a,b):\n    if a == 0:\n            return b\n    while b != 0:\n            if a &gt; b:\n                    a = a - b\n            else:\n                    b = b - a\n    return a \n\ngcd(1,2)\n</code>\n</pre>\n", "senID": 5}, {"text": ["and all will be well."], "childNum": 0, "tag": "p", "senID": 6, "childList": []}], [{"text": ["You could use the staticmethod decorator like this:"], "childNum": 1, "tag": "p", "senID": 0, "childList": [{"text": "staticmethod", "tag": "a", "pos": 0, "childList": [], "childNum": 0, "href": "http://docs.python.org/library/functions.html#staticmethod"}]}, {"code": "<pre>\n<code>\n ...\nclass RSA:    \n\n    @staticmethod\n    def gcd(a,b):\n        ...\n</code>\n</pre>\n", "senID": 1}], [{"text": ["if gcd is a method inside the class then you should define it as follows:"], "childNum": 0, "tag": "p", "senID": 0, "childList": []}, {"text": ["def gcd(self, a, b): etc."], "childNum": 0, "tag": "p", "senID": 1, "childList": []}], [{"text": ["I suspect (since the error is in code you haven't provided) that gcd is actually a method and you are calling it as obj.gcd(a,b).", "This is translated as gcd(self, a, b) = 3 arguments.", "you need to define the function with the self argument."], "childNum": 0, "tag": "p", "senID": 0, "childList": []}], [{"text": ["There's already an accepted answer that solves the problem, but I'd like to point out, that (IMHO) a more idiomatic solution in Python would be to move the gcd method outside the class to a plain function in the module."], "childNum": 1, "tag": "p", "senID": 0, "childList": [{"text": "gcd", "childNum": 0, "tag": "code", "pos": 0, "childList": []}]}, {"text": ["I mean, it's a general purpose function.", "There's no reason in Python to encapsulate it in a class."], "childNum": 0, "tag": "p", "senID": 1, "childList": []}], [{"text": ["I just threw that code into Python (in interpreter mode) and it seems to work just fine.", "Are you sure gcd isn't being redefined anywhere?", "Python will allow you to redefine functions without warning, if I remember correctly."], "childNum": 0, "tag": "p", "senID": 0, "childList": []}], [{"text": ["The code as you provide it, works fine in an interpreter.", "If you're calling gcd() as a method, you need to add \"self\" as first argument."], "childNum": 0, "tag": "p", "senID": 0, "childList": []}, {"code": "<pre>\n<code>\n def gcd(self, a, b):\n        //...\n</code>\n</pre>\n", "senID": 1}]]