[[{"text": ["From the Python REPL (the command-line interpreter / Read-Eval-Print-Loop), type help(\"modules\") to see a list of all your available libs."], "childNum": 1, "tag": "p", "senID": 0, "childList": [{"text": "help(\"modules\")", "childNum": 0, "tag": "code", "pos": 0, "childList": []}]}, {"text": ["Then to see functions within a module, do help(\"posix\"), for example.", "If you haven't imported the library yet, you have to put quotes around the library's name."], "childNum": 2, "tag": "p", "senID": 1, "childList": [{"text": "help(\"posix\")", "childNum": 0, "tag": "code", "pos": 0, "childList": []}, {"text": "import", "childNum": 0, "tag": "code", "pos": 1, "childList": []}]}], [{"text": ["Every standard python distribution has these libraries, which cover most of what you will need in a project."], "childNum": 1, "tag": "p", "senID": 0, "childList": [{"text": "these", "tag": "a", "pos": 0, "childList": [], "childNum": 0, "href": "http://docs.python.org/library/index.html"}]}, {"text": ["In case you need to find out if a library exists at runtime, you do it like this"], "childNum": 0, "tag": "p", "senID": 1, "childList": []}, {"code": "<pre>\n<code>\n try:\n    import ObscureModule\nexcept ImportError:\n    print \"you need to install ObscureModule\"\n    sys.exit(1) # or something like that\n</code>\n</pre>\n", "senID": 2}], [{"text": ["On Leopard, depending on the python package you're using and the version number, the modules can be found in /Library/Python:"], "childNum": 0, "tag": "p", "senID": 0, "childList": []}, {"text": ["/Library/Python/2.5/site-packages"], "childNum": 0, "tag": "p", "senID": 1, "childList": []}, {"text": ["or in /Library/Frameworks"], "childNum": 0, "tag": "p", "senID": 2, "childList": []}, {"text": ["/Library/Frameworks/Python.framework/Versions/Current/lib/python2.6/site-packages"], "childNum": 0, "tag": "p", "senID": 3, "childList": []}, {"text": ["(it could also be 3.0 or whatever version)...", "I guess it is quite the same with Tiger"], "childNum": 0, "tag": "p", "senID": 4, "childList": []}], [{"text": ["You can install another library: yolk."], "childNum": 0, "tag": "p", "senID": 0, "childList": []}, {"text": ["yolk is a python package manager and will show you everything you have added via pypi.", "But it will also show you site-packages added through whatever local package manager you run."], "childNum": 0, "tag": "p", "senID": 1, "childList": []}], [{"text": ["For the web server, you can run the pydoc module that is included in the python distribution as a script:"], "childNum": 1, "tag": "p", "senID": 0, "childList": [{"text": "pydoc", "childNum": 0, "tag": "code", "pos": 0, "childList": []}]}, {"code": "<pre>\n<code>\n python /path/to/pydoc.py -p 1234\n</code>\n</pre>\n", "senID": 1}, {"text": ["where 1234 is the port you want the server to run at.", "You can then visit http://localhost:1234/ and browse the documentation. "], "childNum": 2, "tag": "p", "senID": 2, "childList": [{"text": "1234", "childNum": 0, "tag": "code", "pos": 0, "childList": []}, {"text": "http://localhost:1234/", "childNum": 0, "tag": "code", "pos": 1, "childList": []}]}], [{"text": ["just run the Python interpeter and type the command\nimport \"lib_name\" \nif it gives an error, you don't have the lib installed...else you are good to go"], "childNum": 0, "tag": "p", "senID": 0, "childList": []}]]