[[{"text": ["You can use a list comprehension to make it shorter.", "Use the if to account for the empty string."], "childNum": 1, "tag": "p", "senID": 0, "childList": [{"text": "if", "childNum": 0, "tag": "code", "pos": 1, "childList": []}]}, {"code": "<pre>\n<code>\n the_string = '1-2-3-4'\n\n[int(x) for x in the_string.split('-') if x != '']\n</code>\n</pre>\n", "senID": 1}], [{"code": "<pre>\n<code>\n &gt;&gt;&gt; for s in [\"\", \"0\", \"-0-0\", \"1-2-3-4\"]:\n...     print(map(int, filter(None, s.split('-'))))\n... \n[]\n[0]\n[0, 0]\n[1, 2, 3, 4]\n</code>\n</pre>\n", "senID": 0}], [{"text": ["Convert the higher-order functions to a more readable list-comprehension"], "childNum": 0, "tag": "p", "senID": 0, "childList": []}, {"code": "<pre>\n<code>\n [ int(n) for n in \"1-2-3-4\".split('-') if n != '' ]\n</code>\n</pre>\n", "senID": 1}, {"text": ["The rest is fine."], "childNum": 0, "tag": "p", "senID": 2, "childList": []}], [{"text": ["From the format of your example, you want int's in the list.", "If so, then you will need to convert the string numbers to int's.", "If not, then you are done after the string split."], "childNum": 0, "tag": "p", "senID": 0, "childList": []}, {"code": "<pre>\n<code>\n text=\"1-2-3-4\"\n\nnumlist=[int(ith) for ith in text.split('-')]\nprint numlist\n[1, 2, 3, 4]\n\ntextlist=text.split('-')\nprint textlist\n['1', '2', '3', '4']\n</code>\n</pre>\n", "senID": 1}, {"text": ["EDIT:  Revising my answer to reflect the update in the question."], "childNum": 0, "tag": "p", "senID": 2, "childList": []}, {"text": ["If the list can be malformed then \"try...catch\" if your friend.", "This will enforce that the list is either well formed, or you get an empty list.  "], "childNum": 0, "tag": "p", "senID": 3, "childList": []}, {"code": "<pre>\n<code>\n &gt;&gt;&gt; def convert(input):\n...     try:\n...         templist=[int(ith) for ith in input.split('-')]\n...     except:\n...         templist=[]\n...     return templist\n...     \n&gt;&gt;&gt; convert('1-2-3-4')\n[1, 2, 3, 4]\n&gt;&gt;&gt; convert('')\n[]\n&gt;&gt;&gt; convert('----1-2--3--4---')\n[]\n&gt;&gt;&gt; convert('Explicit is better than implicit.')\n[]\n&gt;&gt;&gt; convert('1-1 = 0')\n[]\n</code>\n</pre>\n", "senID": 4}], [{"text": ["I'd go with this:"], "childNum": 0, "tag": "p", "senID": 0, "childList": []}, {"code": "<pre>\n<code>\n &gt;&gt;&gt; the_string = '1-2-3-4- -5-   6-'\n&gt;&gt;&gt;\n&gt;&gt;&gt; [int(x.strip()) for x in the_string.split('-') if len(x)]\n[1, 2, 3, 4, 5, 6]\n</code>\n</pre>\n", "senID": 1}], [{"code": "<pre>\n<code>\n def convert(s):\n    if s:\n        return map(int, s.split(\"-\"))\n    else:\n        return []\n</code>\n</pre>\n", "senID": 0}], [{"text": ["you don't need the lambda, and split won't give you empty elements:"], "childNum": 0, "tag": "p", "senID": 0, "childList": []}, {"code": "<pre>\n<code>\n map(int, filter(None,x.split(\"-\")))\n</code>\n</pre>\n", "senID": 1}]]